termtables/__about__.py
termtables/__init__.py
termtables/main.py
termtables/styles.py
termtables-0.2.4.dist-info/LICENSE
termtables-0.2.4.dist-info/METADATA
termtables-0.2.4.dist-info/WHEEL
termtables-0.2.4.dist-info/top_level.txt
termtables-0.2.4.dist-info/RECORD
